spider/__init__.py
spider/setting.py
spider/controller/__init__.py
spider/controller/controller.py
spider/controller/database.py
spider/controller/main.py
spider/lib/__init__.py
spider/lib/cookie.py
spider/lib/database.py
spider/lib/dingtalk.py
spider/lib/headers.py
spider/lib/json_format.py
spider/lib/redis.py
spider/lib/tools.py
spider/model/__init__.py
spider/model/model.py
spider/model/queue_list.py
python_spider-1.0.0.dist-info/LICENSE
python_spider-1.0.0.dist-info/METADATA
python_spider-1.0.0.dist-info/WHEEL
python_spider-1.0.0.dist-info/top_level.txt
python_spider-1.0.0.dist-info/RECORD
