Metadata-Version: 2.1
Name: python-spider
Version: 1.0.0
Summary: personal python spider frame
Home-page: https://github.com/ticowong
Author: tico.wong
Author-email: ticowong@163.com
License: BSD License
Platform: UNKNOWN
Classifier: Intended Audience :: Developers
Classifier: Operating System :: OS Independent
Classifier: Natural Language :: Chinese (Simplified)
Classifier: Programming Language :: Python
Classifier: Programming Language :: Python :: 3.7
Classifier: Programming Language :: Python :: 3.8
Classifier: Programming Language :: Python :: 3.9
Classifier: Topic :: Software Development :: Libraries
Requires-Dist: pymysql (==0.9.3)
Requires-Dist: requests (==2.24.0)
Requires-Dist: aiohttp (==3.7.3)
Requires-Dist: DBUtils (==2.0)
Requires-Dist: aioredis (==1.3.1)
Requires-Dist: aiomysql (==0.0.21)
Requires-Dist: redis (==3.2.1)
Requires-Dist: protobuf (==3.20.1)
Requires-Dist: aliyun-log-python-sdk (==0.7.11)
Requires-Dist: wheel (==0.37.1)
Requires-Dist: kafka-python (==2.0.2)
